req2flatpak.py
req2flatpak-0.3.1.dist-info/COPYING
req2flatpak-0.3.1.dist-info/METADATA
req2flatpak-0.3.1.dist-info/WHEEL
req2flatpak-0.3.1.dist-info/entry_points.txt
req2flatpak-0.3.1.dist-info/RECORD
