Metadata-Version: 2.3
Name: req2flatpak
Version: 0.3.1
Summary: Generates a flatpak-builder build module for installing python packages defined in requirements.txt files.
License: MIT
Author: johannesjh
Author-email: johannesjh@users.noreply.github.com
Requires-Python: >=3.8
Classifier: License :: OSI Approved :: MIT License
Classifier: Programming Language :: Python :: 3
Classifier: Programming Language :: Python :: 3.8
Classifier: Programming Language :: Python :: 3.9
Classifier: Programming Language :: Python :: 3.10
Classifier: Programming Language :: Python :: 3.11
Classifier: Programming Language :: Python :: 3.12
Classifier: Programming Language :: Python :: 3.13
Provides-Extra: yaml
Requires-Dist: packaging (>=21.3,<22.0)
Requires-Dist: pyyaml (>=6.0.1,<7.0.0) ; extra == "yaml"
